loregrep-0.4.2.dist-info/METADATA
loregrep-0.4.2.dist-info/WHEEL
loregrep-0.4.2.dist-info/licenses/LICENSE-APACHE
loregrep-0.4.2.dist-info/licenses/LICENSE-MIT
loregrep.libs/libgcc_s-b5472b99.so.1
loregrep/__init__.py
loregrep/loregrep.cpython-310-i386-linux-gnu.so
loregrep-0.4.2.dist-info/RECORD
