Metadata-Version: 2.4
Name: loregrep
Version: 0.4.2
Classifier: Development Status :: 4 - Beta
Classifier: Intended Audience :: Developers
Classifier: License :: OSI Approved :: MIT License
Classifier: License :: OSI Approved :: Apache Software License
Classifier: Programming Language :: Python :: 3
Classifier: Programming Language :: Python :: 3.8
Classifier: Programming Language :: Python :: 3.9
Classifier: Programming Language :: Python :: 3.10
Classifier: Programming Language :: Python :: 3.11
Classifier: Programming Language :: Python :: 3.12
Classifier: Programming Language :: Rust
Classifier: Topic :: Software Development :: Libraries :: Python Modules
Classifier: Topic :: Text Processing :: Linguistic
Requires-Dist: pytest>=7.0 ; extra == 'dev'
Requires-Dist: pytest-asyncio>=0.21.0 ; extra == 'dev'
Requires-Dist: black>=22.0 ; extra == 'dev'
Requires-Dist: isort>=5.0 ; extra == 'dev'
Requires-Dist: mypy>=1.0 ; extra == 'dev'
Provides-Extra: dev
License-File: LICENSE-APACHE
License-File: LICENSE-MIT
Summary: Fast repository indexing and code analysis tools for AI coding assistants - 6 standardized tools for Claude, GPT, and more
Keywords: ai,claude,gpt,code-analysis,tree-sitter,coding-assistant,repository-indexing,python,llm
Home-Page: https://github.com/Vasu014/loregrep
Author: Vasu Bhardwaj <voodoorapter014@gmail.com>
Author-email: Vasu Bhardwaj <voodoorapter014@gmail.com>
License: MIT OR Apache-2.0
Requires-Python: >=3.8
Project-URL: Homepage, https://github.com/Vasu014/loregrep
Project-URL: Repository, https://github.com/Vasu014/loregrep
Project-URL: Issues, https://github.com/Vasu014/loregrep/issues
